[{"s": "hisense-stiralnaya-mashina-proizvoditel", "t": "Hisense стиральная машина: кто производитель и где собирают", "i": "🧺", "c": "bytovaya-tekhnika"}, {"s": "hinge-perevod-na-russkij", "t": "Hinge: перевод на русский и значение в автомобильной тематике", "i": "🎨", "c": "kuzov-i-okraska"}, {"s": "hisense-chto-za-proizvoditel", "t": "Hisense: что за бренд, история, плюсы и минусы техники", "i": "🧺", "c": "bytovaya-tekhnika"}, {"s": "hi-gear-promyvka-sistemy-okhlazhdeniya", "t": "Hi-Gear промывка системы охлаждения: инструкция и отзывы 2026", "i": "⚙️", "c": "dvigatel-i-to"}, {"s": "hino-gruzovik-strana-proizvoditel", "t": "Страна производитель грузовиков Hino: Япония или Индонезия?", "i": "⚙️", "c": "dvigatel-i-to"}, {"s": "hiphi-z-120-kwh", "t": "HiPhi Z 120 kWh: Обзор электрокара с запасом хода", "i": "⚡", "c": "elektrika-avto"}, {"s": "high-beam-perevod-na-russkij", "t": "High Beam перевод на русский: обозначение и использование", "i": "🎓", "c": "obuchenie-i-testy"}, {"s": "hitch-perevod-na-russkij", "t": "Hitch перевод на русский: значение слова и использование", "i": "🧢", "c": "aksessuary-i-tyuning"}, {"s": "hi-low-chto-eto", "t": "Hi-Lo в картах и казино: что это, правила и стратегии", "i": "🎓", "c": "obuchenie-i-testy"}, {"s": "high-power-m33-puskovoe-ustrojstvo", "t": "Пусковое устройство High Power M33: обзор, характеристики и тест", "i": "🔧", "c": "instrumenty"}, {"s": "hisense-stiralnaya-mashina-otzyvy-masterov", "t": "Hisense стиральная машина: отзывы мастеров, поломки и ремонт", "i": "🧺", "c": "bytovaya-tekhnika"}]