[{"s": "sfericheskoe-zerkalo-chto-eto", "t": "Сферическое зеркало: устройство, виды и применение в автооптике", "i": "🧢", "c": "aksessuary-i-tyuning"}, {"s": "sfri-ru-proverit-parkovochnoe-razreshenie-invalida", "t": "Как проверить парковочное разрешение инвалида на sfri.ru в 2026 году", "i": "⚖️", "c": "zakony-i-shtrafy"}, {"s": "sfericheskie-zerkala-chto-eto", "t": "Сферические зеркала в автомобилях: устройство, виды и применение", "i": "🧢", "c": "aksessuary-i-tyuning"}, {"s": "sfri-ru-proverit-parkovochnoe-razreshenie", "t": "sfri.ru проверка парковочного разрешения: инструкция", "i": "⚖️", "c": "zakony-i-shtrafy"}, {"s": "sfericheskie-zerkala-dlya-avto", "t": "Сферические зеркала для авто: обзор, установка и регулировка", "i": "🧢", "c": "aksessuary-i-tyuning"}]