[{"s": "www-cars-auto-ru", "t": "WWW.CARS.AUTO.RU: отзывы, возможности и альтернативы для автовладельцев", "i": "🤝", "c": "pokupka-i-prodazha"}, {"s": "www-drom-ru-primorskij", "t": "Drom.ru в Приморском крае: как купить и продать авто выгодно в 2026", "i": "🤝", "c": "pokupka-i-prodazha"}, {"s": "www-auto-ru-avto-s-probegom", "t": "Авто с пробегом на auto.ru: поиск, проверка и покупка", "i": "🤝", "c": "pokupka-i-prodazha"}, {"s": "www-reestr-zalogov-ru", "t": "Реестр залогов движимого имущества: проверка и выписки", "i": "⚖️", "c": "zakony-i-shtrafy"}]